easysmtp-0.1.5.dist-info/METADATA
easysmtp-0.1.5.dist-info/WHEEL
easysmtp-0.1.5.dist-info/entry_points.txt
easysmtp-0.1.5.dist-info/licenses/LICENSE
easysmtp.py
easysmtp-0.1.5.dist-info/RECORD
