Metadata-Version: 2.1
Name: easysmtp
Version: 0.1.5
Summary: A simple SMTP client.
Author-Email: Inpool <inpool@126.com>
License: BSD-3-Clause
Classifier: License :: OSI Approved :: BSD License
Classifier: Programming Language :: Python :: 3.8
Classifier: Programming Language :: Python :: 3.9
Classifier: Programming Language :: Python :: 3.10
Classifier: Programming Language :: Python :: 3.11
Project-URL: Source, https://github.com/inpool/easysmtp
Requires-Python: >=3.8
